LICENSE
README.md
setup.py
jboat/__init__.py
jboat/boat_opt.py
jboat/operation_registry.py
jboat.egg-info/PKG-INFO
jboat.egg-info/SOURCES.txt
jboat.egg-info/dependency_links.txt
jboat.egg-info/requires.txt
jboat.egg-info/top_level.txt
jboat/fo_ol/__init__.py
jboat/fo_ol/meso.py
jboat/fo_ol/pgdo.py
jboat/fo_ol/vfo.py
jboat/fo_ol/vso.py
jboat/gm_ol/__init__.py
jboat/gm_ol/di.py
jboat/gm_ol/dm.py
jboat/gm_ol/dynamical_system.py
jboat/gm_ol/gda.py
jboat/gm_ol/ngd.py
jboat/gm_ol/sequential_ds.py
jboat/higher_jit/__init__.py
jboat/higher_jit/optim.py
jboat/higher_jit/patch.py
jboat/higher_jit/utils.py
jboat/na_ol/__init__.py
jboat/na_ol/cg.py
jboat/na_ol/fd.py
jboat/na_ol/foa.py
jboat/na_ol/hyper_gradient.py
jboat/na_ol/iad.py
jboat/na_ol/iga.py
jboat/na_ol/ns.py
jboat/na_ol/ptt.py
jboat/na_ol/rad.py
jboat/na_ol/rgt.py
jboat/na_ol/sequential_hg.py
jboat/utils/__init__.py
jboat/utils/op_utils.py