Metadata-Version: 2.1
Name: jboat
Version: 0.0.1
Summary: BOAT: A Compositional Operation Toolbox for Gradient-based Bi-Level Optimization
Home-page: https://github.com/vis-opt-group/JBOAT
Author: Yaohua Liu, Jibao Pan, Xianghao Jiao, Jiaxin Gao, Zhu Liu, Risheng Liu
Author-email: liuyaohua.918@gmail.com
License: MIT
Keywords: Bilevel-optimization,Learning and vision,Python,Deep learning,Jittor
Classifier: License :: OSI Approved :: MIT License
Classifier: Programming Language :: Python :: 3
Classifier: Programming Language :: Python :: 3.8
Classifier: Programming Language :: Python :: 3.9
Classifier: Programming Language :: Python :: 3.10
Classifier: Programming Language :: Python :: 3.11
Classifier: Operating System :: OS Independent
Requires-Python: >=3.8.0
License-File: LICENSE
Requires-Dist: setuptools
Requires-Dist: numpy
Requires-Dist: tqdm
Requires-Dist: jittor
Requires-Dist: matplotlib
